spicedmodel/Density.py
spicedmodel/Mav.py
spicedmodel/MavHot.py
spicedmodel/MavPS.py
spicedmodel/MavPT.py
spicedmodel/PMD.py
spicedmodel/PS.py
spicedmodel/PT.py
spicedmodel/PlotEq.py
spicedmodel/PlotPlanet.py
spicedmodel/Prob.py
spicedmodel/_CFunctions.py
spicedmodel/_CTConv.py
spicedmodel/__init__.py
spicedmodel/__data/liblsmodel/activationfunctions.cc
spicedmodel/__data/liblsmodel/activationfunctions.h
spicedmodel/__data/liblsmodel/activationfunctions.o
spicedmodel/__data/liblsmodel/annmavhmodel.cc
spicedmodel/__data/liblsmodel/annmavhmodel.h
spicedmodel/__data/liblsmodel/annmavhmodel.o
spicedmodel/__data/liblsmodel/annmavpsmodel.cc
spicedmodel/__data/liblsmodel/annmavpsmodel.h
spicedmodel/__data/liblsmodel/annmavpsmodel.o
spicedmodel/__data/liblsmodel/annmavptmodel.cc
spicedmodel/__data/liblsmodel/annmavptmodel.h
spicedmodel/__data/liblsmodel/annmavptmodel.o
spicedmodel/__data/liblsmodel/annmodel.cc
spicedmodel/__data/liblsmodel/annmodel.h
spicedmodel/__data/liblsmodel/annmodel.o
spicedmodel/__data/liblsmodel/annprobmodel.cc
spicedmodel/__data/liblsmodel/annprobmodel.h
spicedmodel/__data/liblsmodel/annprobmodel.o
spicedmodel/__data/liblsmodel/annpsmodel.cc
spicedmodel/__data/liblsmodel/annpsmodel.h
spicedmodel/__data/liblsmodel/annpsmodel.o
spicedmodel/__data/liblsmodel/annptmodel.cc
spicedmodel/__data/liblsmodel/annptmodel.h
spicedmodel/__data/liblsmodel/annptmodel.o
spicedmodel/__data/liblsmodel/arraytools.cc
spicedmodel/__data/liblsmodel/arraytools.h
spicedmodel/__data/liblsmodel/avmavhmodel.cc
spicedmodel/__data/liblsmodel/avmavhmodel.h
spicedmodel/__data/liblsmodel/avmavhmodel.o
spicedmodel/__data/liblsmodel/avmavpsmodel.cc
spicedmodel/__data/liblsmodel/avmavpsmodel.h
spicedmodel/__data/liblsmodel/avmavpsmodel.o
spicedmodel/__data/liblsmodel/avmavptmodel.cc
spicedmodel/__data/liblsmodel/avmavptmodel.h
spicedmodel/__data/liblsmodel/avmavptmodel.o
spicedmodel/__data/liblsmodel/avmodel.cc
spicedmodel/__data/liblsmodel/avmodel.h
spicedmodel-1.0.0.dist-info/LICENSE
spicedmodel-1.0.0.dist-info/METADATA
spicedmodel-1.0.0.dist-info/WHEEL
spicedmodel-1.0.0.dist-info/top_level.txt
spicedmodel-1.0.0.dist-info/RECORD
