Metadata-Version: 2.1
Name: spicedmodel
Version: 1.0.0
Summary: Python wrapper for the Scalable Plasma Ion Composition and Electron Density (SPICED) model
Home-page: https://github.com/mattkjames7/spicedmodel
Author: Matthew Knight James
Author-email: mattkjames7@gmail.com
License: UNKNOWN
Platform: UNKNOWN
Classifier: Programming Language :: Python :: 3
Classifier: License :: OSI Approved :: GNU General Public License (GPL)
Classifier: Operating System :: POSIX
Requires-Dist: numpy
Requires-Dist: matplotlib
